Workbook

Sheet README
A1: PROJET DATA ANALYST — ANALYSE DES VENTES
A3: Contexte | B3: Vous êtes Data Analyst junior dans une entreprise fictive de commerce. La direction souhaite comprendre les performances commerciales du premier semestre 2026.
A4: Objectif | B4: Nettoyer les données, calculer les indicateurs clés, analyser les ventes et présenter les résultats sous forme de dashboard.
A5: Outils | B5: Excel : nettoyage, formules, tableaux croisés dynamiques, graphiques et analyse.
A6: Étape 1 | B6: Inspecter Données_brutes et repérer les incohérences.
A7: Étape 2 | B7: Reproduire les corrections dans Données_nettoyées.
A8: Étape 3 | B8: Calculer CA total, commandes, quantité vendue et panier moyen.
A9: Étape 4 | B9: Analyser les ventes par mois, catégorie, produit, région et canal.
A10: Étape 5 | B10: Construire un dashboard clair.
A11: Étape 6 | B11: Rédiger 3 à 5 insights et recommandations.
A12: Important | B12: Les données brutes contiennent volontairement quelques incohérences : le but est de pratiquer comme une vraie Data Analyst.

Sheet Données_brutes
A1: Commande | B1: Date | C1: Client_ID | D1: Région | E1: Canal | F1: Catégorie | G1: Produit | H1: Quantité | I1: Prix_unitaire | J1: Paiement | K1: Chiffre_affaires
A2: CMD0102 | B2: 46023 | C2: C1182 | D2: Nouvelle-Aquitaine | E2: Site web | F2: Électronique | G2: Batterie externe | H2: 1 | I2: 35 | J2: Carte bancaire | K2: 35
A3: CMD0157 | B3: 46023 | C3: C1025 | D3: Occitanie | E3: Application mobile | F3: Maison | G3: Cafetière | H3: 1 | I3: 89.1 | J3: Carte bancaire | K3: 89.1
A4: CMD0295 | B4: 46023 | C4: C1245 | D4: Île-de-France | E4: Application mobile | F4: Maison | G4: Aspirateur balai | H4: 1 | I4: 187.95 | J4: Carte bancaire | K4: 187.95
A5: CMD0325 | B5: 46023 | C5: C1034 | D5: Île-de-France | E5: Site web | F5: Sport | G5: Haltères | H5: 1 | I5: 40.5 | J5: Carte bancaire | K5: 40.5
A6: CMD0470 | B6: 46023 | C6: C1032 | D6: Île-de-France | E6: Application mobile | F6: Sport | G6: Gourde | H6: 1 | I6: 19.8 | J6: Carte bancaire | K6: 19.8
A7: CMD0115 | B7: 46024 | C7: C1130 | D7: Auvergne-Rhône-Alpes | E7: Site web | F7: Beauté | G7: Sèche-cheveux | H7: 1 | I7: 120 | J7: PayPal | K7: 120
A8: CMD0269 | B8: 46025 | C8: C1220 | D8: Île-de-France | E8: Site web | F8: Beauté | G8: Shampooing | H8: 5 | I8: 16.2 | J8: Apple Pay | K8: 81
A9: CMD0380 | B9: 46025 | C9: C1183 | D9: Auvergne-Rhône-Alpes | E9: Site web | F9: Électronique | G9: Casque audio | H9: 2 | I9: 82.95 | J9: Carte bancaire | K9: 165.9
A10: CMD0246 | B10: 46026 | C10: C1055 | D10: Occitanie | E10: Site web | F10: Vêtements | G10: Sweat | H10: 1 | I10: 55 | J10: Carte bancaire | K10: 55
A11: CMD0140 | B11: 46027 | C11: C1122 | D11: Auvergne-Rhône-Alpes | E11: Site web | F11: Électronique | G11: Casque audio | H11: 2 | I11: 79 | J11: Carte bancaire | K11: 158
A12: CMD0177 | B12: 46027 | C12: C1151 | D12: Auvergne-Rhône-Alpes | E12: Site web | F12: Maison | G12: Bouilloire | H12: 1 | I12: 47.25 | J12: Carte bancaire | K12: 47.25
A13: CMD0185 | B13: 46027 | C13: C1171 | D13: Occitanie | E13: Application mobile | F13: Beauté | G13: Sérum | H13: 2 | I13: 35 | J13: Carte bancaire | K13: 70
... A601: CMD0225 | B601: 46203 | C601: C1227 | D601: Île-de-France | E601: Application mobile | F601: Sport | G601: Élastiques | H601: 1 | I601: 16.2 | J601: Carte bancaire | K601: 16.2

Sheet Données_nettoyées
A1: Commande | B1: Date | C1: Client_ID | D1: Région | E1: Canal | F1: Catégorie | G1: Produit | H1: Quantité | I1: Prix_unitaire | J1: Paiement | K1: Chiffre_affaires
A2: CMD0102 | B2: 46023 | C2: C1182 | D2: Nouvelle-Aquitaine | E2: Site web | F2: Électronique | G2: Batterie externe | H2: 1 | I2: 35 | J2: Carte bancaire | K2: 35
A3: CMD0157 | B3: 46023 | C3: C1025 | D3: Occitanie | E3: Application mobile | F3: Maison | G3: Cafetière | H3: 1 | I3: 89.1 | J3: Carte bancaire | K3: 89.1
A4: CMD0295 | B4: 46023 | C4: C1245 | D4: Île-de-France | E4: Application mobile | F4: Maison | G4: Aspirateur balai | H4: 1 | I4: 187.95 | J4: Carte bancaire | K4: 187.95
A5: CMD0325 | B5: 46023 | C5: C1034 | D5: Île-de-France | E5: Site web | F5: Sport | G5: Haltères | H5: 1 | I5: 40.5 | J5: Carte bancaire | K5: 40.5
A6: CMD0470 | B6: 46023 | C6: C1032 | D6: Île-de-France | E6: Application mobile | F6: Sport | G6: Gourde | H6: 1 | I6: 19.8 | J6: Carte bancaire | K6: 19.8
A7: CMD0115 | B7: 46024 | C7: C1130 | D7: Auvergne-Rhône-Alpes | E7: Site web | F7: Beauté | G7: Sèche-cheveux | H7: 1 | I7: 120 | J7: PayPal | K7: 120
A8: CMD0269 | B8: 46025 | C8: C1220 | D8: Île-de-France | E8: Site web | F8: Beauté | G8: Shampooing | H8: 5 | I8: 16.2 | J8: Apple Pay | K8: 81
A9: CMD0380 | B9: 46025 | C9: C1183 | D9: Auvergne-Rhône-Alpes | E9: Site web | F9: Électronique | G9: Casque audio | H9: 2 | I9: 82.95 | J9: Carte bancaire | K9: 165.9
A10: CMD0246 | B10: 46026 | C10: C1055 | D10: Occitanie | E10: Site web | F10: Vêtements | G10: Sweat | H10: 1 | I10: 55 | J10: Carte bancaire | K10: 55
A11: CMD0140 | B11: 46027 | C11: C1122 | D11: Auvergne-Rhône-Alpes | E11: Site web | F11: Électronique | G11: Casque audio | H11: 2 | I11: 79 | J11: Carte bancaire | K11: 158
A12: CMD0177 | B12: 46027 | C12: C1151 | D12: Auvergne-Rhône-Alpes | E12: Site web | F12: Maison | G12: Bouilloire | H12: 1 | I12: 47.25 | J12: Carte bancaire | K12: 47.25
A13: CMD0185 | B13: 46027 | C13: C1171 | D13: Occitanie | E13: Application mobile | F13: Beauté | G13: Sérum | H13: 2 | I13: 35 | J13: Carte bancaire | K13: 70
... A601: CMD0225 | B601: 46203 | C601: C1227 | D601: Île-de-France | E601: Application mobile | F601: Sport | G601: Élastiques | H601: 1 | I601: 16.2 | J601: Carte bancaire | K601: 16.2

Sheet Analyse
A1: ANALYSE DES PERFORMANCES COMMERCIALES
I2: QUESTIONS BUSINESS & RÉPONSES
A3: INDICATEURS CLÉS | I3: Évolution du chiffre d'affaires | J3: Le CA passe de 12 180,70 € en janvier à 10 200,45 € en juin, soit une baisse de 16,3 %. Après un pic à 12 442,50 € en mars, le CA diminue chaque mois jusqu'en juin.
A4: Chiffre d'affaires total | B4: =SUM(Données_nettoyées!K2:K601) -> 68396.05 | I4: Catégorie la plus performante | J4: La catégorie Maison génère le CA le plus élevé avec 19 273,40 €, soit 28,2 % du CA total. Elle est suivie par l'Électronique avec 16 983,80 €.
A5: Nombre de commandes | B5: =COUNTA(Données_nettoyées!A2:A601) -> 600 | I5: Mois le plus performant | J5: Mars est le mois le plus performant avec 12 442,50 € de CA, soit le niveau le plus élevé du semestre.
A6: Quantité vendue | B6: =SUM(Données_nettoyées!H2:H601) -> 1155 | I6: Produits les plus performants | J6: La Cafetière (6 880,50 €), l'Aspirateur balai (6 381,35 €) et le Sèche-cheveux (5 532,00 €) sont les trois produits générant le plus de CA.
A7: Panier moyen | B7: =SUM(Données_nettoyées!K2:K601)/COUNTA(Données_nettoyées!A2:A601) -> 113.99342 | I7: Région et canal générant le plus de CA | J7: L'Île-de-France génère le CA régional le plus élevé avec 22 318,80 € (32,6 %). Le site web est le premier canal avec 32 565,85 € (47,6 % du CA).
I9: RECOMMANDATIONS
A10: CA PAR MOIS | D10: CA PAR CATÉGORIE | I10: Renforcer le canal web | J10: Le site web génère 47,6 % du CA. Optimiser les campagnes digitales et le parcours d'achat pourrait permettre de soutenir sa croissance.
A11: Mois | B11: CA | D11: Catégorie | E11: CA | F11: Part | I11: Capitaliser sur la catégorie Maison | J11: Avec 28,2% du CA, Maison est la catégorie n°1. Des offres combinées et ventes croisées pourraient augmenter le panier moyen.
A12: Janvier | B12: =SUMIFS(Données_nettoyées!$K$2:$K$601,Données_nettoyées!$B$2:$B$601,">=2026-01-01",Données_nettoyées!$B$2:$B$601,"<2026-02-01") -> 12180.7 | D12: Maison | E12: =SUMIF(Données_nettoyées!$F$2:$F$601,D12,Données_nettoyées!$K$2:$K$601) -> 19273.4 | F12: =E12/SUM($E$12:$E$16) -> 0.28179113 | I12: Investiguer la baisse du CA | J12: Le CA recule après mars et atteint son niveau le plus faible en juin. Une analyse du trafic, des campagnes et du taux de conversion permettrait d'identifier les facteurs associés à cette baisse.
A13: Février | B13: =SUMIFS(Données_nettoyées!$K$2:$K$601,Données_nettoyées!$B$2:$B$601,">=2026-02-01",Données_nettoyées!$B$2:$B$601,"<2026-03-01") -> 11328.7 | D13: Électronique | E13: =SUMIF(Données_nettoyées!$F$2:$F$601,D13,Données_nettoyées!$K$2:$K$601) -> 16983.8 | F13: =E13/SUM($E$12:$E$16) -> 0.24831551
A14: Mars | B14: =SUMIFS(Données_nettoyées!$K$2:$K$601,Données_nettoyées!$B$2:$B$601,">=2026-03-01",Données_nettoyées!$B$2:$B$601,"<2026-04-01") -> 12442.5 | D14: Vêtements | E14: =SUMIF(Données_nettoyées!$F$2:$F$601,D14,Données_nettoyées!$K$2:$K$601) -> 14702 | F14: =E14/SUM($E$12:$E$16) -> 0.21495393
A15: Avril | B15: =SUMIFS(Données_nettoyées!$K$2:$K$601,Données_nettoyées!$B$2:$B$601,">=2026-04-01",Données_nettoyées!$B$2:$B$601,"<2026-05-01") -> 11420.35 | D15: Beauté | E15: =SUMIF(Données_nettoyées!$F$2:$F$601,D15,Données_nettoyées!$K$2:$K$601) -> 11514.75 | F15: =E15/SUM($E$12:$E$16) -> 0.16835402
A16: Mai | B16: =SUMIFS(Données_nettoyées!$K$2:$K$601,Données_nettoyées!$B$2:$B$601,">=2026-05-01",Données_nettoyées!$B$2:$B$601,"<2026-06-01") -> 10823.35 | D16: Sport | E16: =SUMIF(Données_nettoyées!$F$2:$F$601,D16,Données_nettoyées!$K$2:$K$601) -> 5922.1 | F16: =E16/SUM($E$12:$E$16) -> 0.08658541
A17: Juin | B17: =SUMIFS(Données_nettoyées!$K$2:$K$601,Données_nettoyées!$B$2:$B$601,">=2026-06-01",Données_nettoyées!$B$2:$B$601,"<2026-07-01") -> 10200.45
A20: CA PAR RÉGION | D20: CA PAR CANAL
A21: Région | B21: CA | C21: Part | D21: Canal | E21: CA | F21: Part
A22: Île-de-France | B22: =SUMIF(Données_nettoyées!$D$2:$D$601,A22,Données_nettoyées!$K$2:$K$601) -> 22318.8 | C22: =B22/SUM($B$22:$B$26) -> 0.32631709 | D22: Site web | E22: =SUMIF(Données_nettoyées!$E$2:$E$601,D22,Données_nettoyées!$K$2:$K$601) -> 32565.85 | F22: =E22/SUM($E$22:$E$24) -> 0.47613641
A23: Auvergne-Rhône-Alpes | B23: =SUMIF(Données_nettoyées!$D$2:$D$601,A23,Données_nettoyées!$K$2:$K$601) -> 15506.3 | C23: =B23/SUM($B$22:$B$26) -> 0.22671338 | D23: Application mobile | E23: =SUMIF(Données_nettoyées!$E$2:$E$601,D23,Données_nettoyées!$K$2:$K$601) -> 18517.7 | F23: =E23/SUM($E$22:$E$24) -> 0.27074224
A24: Occitanie | B24: =SUMIF(Données_nettoyées!$D$2:$D$601,A24,Données_nettoyées!$K$2:$K$601) -> 13549 | C24: =B24/SUM($B$22:$B$26) -> 0.19809624 | D24: Magasin | E24: =SUMIF(Données_nettoyées!$E$2:$E$601,D24,Données_nettoyées!$K$2:$K$601) -> 17312.5 | F24: =E24/SUM($E$22:$E$24) -> 0.25312134
A25: Nouvelle-Aquitaine | B25: =SUMIF(Données_nettoyées!$D$2:$D$601,A25,Données_nettoyées!$K$2:$K$601) -> 8855.9 | C25: =B25/SUM($B$22:$B$26) -> 0.1294797
A26: Hauts-de-France | B26: =SUMIF(Données_nettoyées!$D$2:$D$601,A26,Données_nettoyées!$K$2:$K$601) -> 8166.05 | C26: =B26/SUM($B$22:$B$26) -> 0.11939359
A29: TOP PRODUITS
A30: Produit | B30: CA | C30: Quantité vendue
A31: Cafetière | B31: 6880.5 | C31: 71
A32: Aspirateur balai | B32: 6381.35 | C32: 36
A33: Sèche-cheveux | B33: 5532 | C33: 46
A34: Clavier mécanique | B34: 5153.1 | C34: 58
A35: Veste | B35: 4554 | C35: 41

Sheet Dashboard
A1: DASHBOARD — PERFORMANCES COMMERCIALES
A2: S1 2026 l Analyse des performances commerciales
A3: CA TOTAL | C3: COMMANDES | E3: QUANTITÉ VENDUE | G3: PANIER MOYEN | J3: Mois | K3: CA | M3: Catégorie | N3: CA
A4: =Analyse!B4 -> 68396.05 | C4: =Analyse!B5 -> 600 | E4: =Analyse!B6 -> 1155 | G4: =Analyse!B7 -> 113.99342 | J4: =Analyse!A12 -> Janvier | K4: =Analyse!B12 -> 12180.7 | M4: =Analyse!D12 -> Maison | N4: =Analyse!E12 -> 19273.4
J5: =Analyse!A13 -> Février | K5: =Analyse!B13 -> 11328.7 | M5: =Analyse!D13 -> Électronique | N5: =Analyse!E13 -> 16983.8
J6: =Analyse!A14 -> Mars | K6: =Analyse!B14 -> 12442.5 | M6: =Analyse!D14 -> Vêtements | N6: =Analyse!E14 -> 14702
J7: =Analyse!A15 -> Avril | K7: =Analyse!B15 -> 11420.35 | M7: =Analyse!D15 -> Beauté | N7: =Analyse!E15 -> 11514.75
J8: =Analyse!A16 -> Mai | K8: =Analyse!B16 -> 10823.35 | M8: =Analyse!D16 -> Sport | N8: =Analyse!E16 -> 5922.1
J9: =Analyse!A17 -> Juin | K9: =Analyse!B17 -> 10200.45
J12: Région | K12: CA | M12: Canal | N12: CA
J13: =Analyse!A22 -> Île-de-France | K13: =Analyse!B22 -> 22318.8 | M13: =Analyse!D22 -> Site web | N13: =Analyse!E22 -> 32565.85
J14: =Analyse!A23 -> Auvergne-Rhône-Alpes | K14: =Analyse!B23 -> 15506.3 | M14: =Analyse!D23 -> Application mobile | N14: =Analyse!E23 -> 18517.7
J15: =Analyse!A24 -> Occitanie | K15: =Analyse!B24 -> 13549 | M15: =Analyse!D24 -> Magasin | N15: =Analyse!E24 -> 17312.5
J16: =Analyse!A25 -> Nouvelle-Aquitaine | K16: =Analyse!B25 -> 8855.9
J17: =Analyse!A26 -> Hauts-de-France | K17: =Analyse!B26 -> 8166.05
A34: INSIGHTS CLÉS
A35: Mars est le meilleur mois : 12 442,50 € de CA. Le CA recule ensuite jusqu'à 10 200,45 € en juin (-16,3% vs janvier).
A36: Maison est la catégorie n°1 : 19 273,40 € de CA, soit 28,2% du CA total.
A37: L'Île-de-France est le premier marché avec 22 318,80 € de CA, soit 32,6 % du CA total.
A38: Le site web domine les canaux : 32 565,85 € de CA, soit 47,6% du CA total.
